odoo9_addon_hr_emergency_contact-9.0.1.0.0.99.dev3-py2.7-nspkg.pth
odoo9_addon_hr_emergency_contact-9.0.1.0.0.99.dev3.dist-info/DESCRIPTION.rst
odoo9_addon_hr_emergency_contact-9.0.1.0.0.99.dev3.dist-info/METADATA
odoo9_addon_hr_emergency_contact-9.0.1.0.0.99.dev3.dist-info/RECORD
odoo9_addon_hr_emergency_contact-9.0.1.0.0.99.dev3.dist-info/WHEEL
odoo9_addon_hr_emergency_contact-9.0.1.0.0.99.dev3.dist-info/metadata.json
odoo9_addon_hr_emergency_contact-9.0.1.0.0.99.dev3.dist-info/namespace_packages.txt
odoo9_addon_hr_emergency_contact-9.0.1.0.0.99.dev3.dist-info/top_level.txt
odoo_addons/hr_emergency_contact/README.rst
odoo_addons/hr_emergency_contact/__init__.py
odoo_addons/hr_emergency_contact/__openerp__.py
odoo_addons/hr_emergency_contact/i18n/ar.po
odoo_addons/hr_emergency_contact/i18n/de.po
odoo_addons/hr_emergency_contact/i18n/es.po
odoo_addons/hr_emergency_contact/i18n/fi.po
odoo_addons/hr_emergency_contact/i18n/fr.po
odoo_addons/hr_emergency_contact/i18n/fr_CH.po
odoo_addons/hr_emergency_contact/i18n/hr_emergency_contact.pot
odoo_addons/hr_emergency_contact/i18n/it.po
odoo_addons/hr_emergency_contact/i18n/nl_NL.po
odoo_addons/hr_emergency_contact/i18n/pt_BR.po
odoo_addons/hr_emergency_contact/i18n/ro.po
odoo_addons/hr_emergency_contact/i18n/sl.po
odoo_addons/hr_emergency_contact/models/__init__.py
odoo_addons/hr_emergency_contact/models/hr_employee.py
odoo_addons/hr_emergency_contact/static/description/icon.png
odoo_addons/hr_emergency_contact/views/hr_employee_views.xml
